{"nodes": { "seere": {"borders": 3, "length": 4000}, "pant": {"borders": 3, "length": 4000}, "shaalu": {"borders": 3, "length": 4000}, "gejje": {"borders": 3, "length": 4000}, "bale": {"borders": 3, "length": 4000}, "sara": {"borders": 3, "length": 4000}, "ungurua": {"borders": 3, "length": 4000}, "choodi dhaar": {"borders": 3, "length": 4000}, "shirtu": {"borders": 3, "length": 4000}, "topi": {"borders": 3, "length": 4000}, "oale": {"borders": 3, "length": 4000}, "chappali": {"borders": 3, "length": 4000}, "sweater": {"borders": 3, "length": 4000}, "karavasthra": {"borders": 3, "length": 4000}}, "edges": {"seere": {"pant": {"border": 600.0},"bale": {"border": 446.0},"shirtu": {"border": 418.0}},"pant": {"shirtu": {"border": 661.0},"seere": {"border": 600.0},"choodi dhaar": {"border": 429.0}},"shaalu": {"sweater": {"border": 631.0},"shirtu": {"border": 312.0},"pant": {"border": 251.0}},"gejje": {"chappali": {"border": 413.0},"bale": {"border": 301.0},"sara": {"border": 275.0}},"bale": {"seere": {"border": 446.0},"oale": {"border": 403.0},"sara": {"border": 401.0}},"sara": {"oale": {"border": 426.0},"bale": {"border": 401.0},"ungurua": {"border": 341.0}},"ungurua": {"sara": {"border": 341.0},"bale": {"border": 275.0},"gejje": {"border": 257.0}},"choodi dhaar": {"pant": {"border": 429.0},"seere": {"border": 389.0},"shirtu": {"border": 334.0}},"shirtu": {"pant": {"border": 661.0},"seere": {"border": 418.0},"choodi dhaar": {"border": 334.0}},"topi": {"shirtu": {"border": 306.0},"pant": {"border": 278.0},"bale": {"border": 273.0}},"oale": {"sara": {"border": 426.0},"bale": {"border": 403.0},"choodi dhaar": {"border": 308.0}},"chappali": {"gejje": {"border": 413.0},"topi": {"border": 239.0},"bale": {"border": 227.0}},"sweater": {"shaalu": {"border": 631.0},"pant": {"border": 268.0},"shirtu": {"border": 244.0}},"karavasthra": {"pant": {"border": 346.0},"shirtu": {"border": 294.0},"seere": {"border": 265.0}}}}
